hygrometry/__init__.py
hygrometry-1.1.1.dist-info/LICENSE
hygrometry-1.1.1.dist-info/METADATA
hygrometry-1.1.1.dist-info/WHEEL
hygrometry-1.1.1.dist-info/top_level.txt
hygrometry-1.1.1.dist-info/RECORD
